bosonnlp/__init__.py
bosonnlp/client.py
bosonnlp/exceptions.py
bosonnlp-0.11.1.dist-info/LICENSE
bosonnlp-0.11.1.dist-info/METADATA
bosonnlp-0.11.1.dist-info/WHEEL
bosonnlp-0.11.1.dist-info/top_level.txt
bosonnlp-0.11.1.dist-info/RECORD
